plexo/__init__.py
plexo/axon.py
plexo/codec/__init__.py
plexo/codec/capnpy_codec.py
plexo/codec/json_codec.py
plexo/codec/pickle_codec.py
plexo/codec/plexo_codec.py
plexo/codec/plexo_multicast_codec.py
plexo/codec/string_codec.py
plexo/dendrite.py
plexo/exceptions.py
plexo/ganglion/__init__.py
plexo/ganglion/external.py
plexo/ganglion/inproc.py
plexo/ganglion/internal.py
plexo/ganglion/plexo_multicast.py
plexo/ganglion/tcp_pair.py
plexo/ganglion/tcp_pubsub.py
plexo/host_information.py
plexo/ip_lease.py
plexo/namespace/__init__.py
plexo/namespace/namespace.py
plexo/neuron/__init__.py
plexo/neuron/neuron.py
plexo/neuron/plexo_multicast_neuron.py
plexo/plexus.py
plexo/schema/__init__.py
plexo/schema/plexo_message.capnp
plexo/schema/plexo_multicast/__init__.py
plexo/schema/plexo_multicast/plexo_approval.capnp
plexo/schema/plexo_multicast/plexo_heartbeat.capnp
plexo/schema/plexo_multicast/plexo_preparation.capnp
plexo/schema/plexo_multicast/plexo_promise.capnp
plexo/schema/plexo_multicast/plexo_proposal.capnp
plexo/schema/plexo_multicast/plexo_rejection.capnp
plexo/synapse/__init__.py
plexo/synapse/base.py
plexo/synapse/inproc.py
plexo/synapse/zeromq_basic.py
plexo/synapse/zeromq_basic_pub.py
plexo/synapse/zeromq_plexopubsub_epgm.py
plexo/timer.py
plexo/transmitter.py
plexo/typing/__init__.py
plexo/typing/codec.py
plexo/typing/ganglion.py
plexo/typing/reactant.py
plexo/typing/synapse.py
plexo/typing/transmitter.py
plexo/schema/plexo_message.py
plexo/schema/plexo_multicast/plexo_approval.py
plexo/schema/plexo_multicast/plexo_heartbeat.py
plexo/schema/plexo_multicast/plexo_preparation.py
plexo/schema/plexo_multicast/plexo_promise.py
plexo/schema/plexo_multicast/plexo_proposal.py
plexo/schema/plexo_multicast/plexo_rejection.py
plexo-1.0.0.dist-info/COPYING
plexo-1.0.0.dist-info/COPYING.LESSER
plexo-1.0.0.dist-info/METADATA
plexo-1.0.0.dist-info/WHEEL
plexo-1.0.0.dist-info/RECORD
