Metadata-Version: 2.1
Name: plexo
Version: 1.0.0
Summary: Opinionated, reactive, schema-driven, distributed, and strongly-typed message passing
Home-page: https://gitlab.com/plexo/pyplexo/
License: LGPL-3.0-or-later
Author: Alecks Gates
Author-email: agates@mail.agates.io
Requires-Python: >=3.9.0,<3.12
Classifier: Development Status :: 5 - Production/Stable
Classifier: Environment :: Console
Classifier: Framework :: AsyncIO
Classifier: Framework :: Pytest
Classifier: License :: OSI Approved :: GNU Lesser General Public License v3 or later (LGPLv3+)
Classifier: Operating System :: POSIX :: Linux
Classifier: Programming Language :: Python :: 3
Classifier: Programming Language :: Python :: 3.9
Classifier: Programming Language :: Python :: 3.10
Classifier: Programming Language :: Python :: 3.11
Classifier: Programming Language :: Python :: 3 :: Only
Classifier: Programming Language :: Python :: Implementation :: CPython
Classifier: Programming Language :: Python :: Implementation :: PyPy
Classifier: Topic :: Adaptive Technologies
Classifier: Topic :: Home Automation
Classifier: Topic :: Internet
Classifier: Topic :: Software Development :: Libraries
Classifier: Topic :: Software Development :: Libraries :: Python Modules
Requires-Dist: capnpy (>=0.10.0,<0.11.0)
Requires-Dist: pyrsistent (>=0.20.0,<0.21.0)
Requires-Dist: python-jsonschema-objects (>=0.5.0,<0.6.0)
Requires-Dist: pyzmq (>=25.0.0,<26.0.0)
Requires-Dist: returns (>=0.22.0,<0.23.0)
Requires-Dist: typing_extensions (>=4.0,<5.0)
Project-URL: Repository, https://gitlab.com/plexo/pyplexo/
